MANIFEST.in
README.md
README.rst
setup.py
django_quiz_app.egg-info/PKG-INFO
django_quiz_app.egg-info/SOURCES.txt
django_quiz_app.egg-info/dependency_links.txt
django_quiz_app.egg-info/not-zip-safe
django_quiz_app.egg-info/requires.txt
django_quiz_app.egg-info/top_level.txt
essay/__init__.py
essay/models.py
essay/tests.py
essay/locale/ru/LC_MESSAGES/django.mo
essay/locale/ru/LC_MESSAGES/django.po
multichoice/__init__.py
multichoice/models.py
multichoice/tests.py
multichoice/locale/ru/LC_MESSAGES/django.mo
multichoice/locale/ru/LC_MESSAGES/django.po
quiz/__init__.py
quiz/admin.py
quiz/forms.py
quiz/models.py
quiz/tests.py
quiz/urls.py
quiz/views.py
quiz/locale/ru/LC_MESSAGES/django.mo
quiz/locale/ru/LC_MESSAGES/django.po
quiz/templates/base.html
quiz/templates/correct_answer.html
quiz/templates/progress.html
quiz/templates/question.html
quiz/templates/result.html
quiz/templates/single_complete.html
quiz/templates/view_quiz_category.html
quiz/templates/quiz/category_list.html
quiz/templates/quiz/quiz_detail.html
quiz/templates/quiz/quiz_list.html
quiz/templates/quiz/sitting_detail.html
quiz/templates/quiz/sitting_list.html
quiz/templatetags/__init__.py
quiz/templatetags/quiz_tags.py
true_false/__init__.py
true_false/models.py
true_false/tests.py
true_false/locale/ru/LC_MESSAGES/django.mo
true_false/locale/ru/LC_MESSAGES/django.po