Metadata-Version: 1.1
Name: django-quiz-app
Version: 0.5.1
Summary: A configurable quiz app for Django.
Home-page: https://github.com/tomwalker/django_quiz
Author: Tom Walker
Author-email: tomwalker0472@gmail.com
License: MIT License
Platform: UNKNOWN
Classifier: Environment :: Web Environment
Classifier: Framework :: Django
Classifier: Intended Audience :: Developers
Classifier: License :: OSI Approved :: MIT License
Classifier: Operating System :: OS Independent
Classifier: Programming Language :: Python
Classifier: Programming Language :: Python :: 2.6
Classifier: Programming Language :: Python :: 2.7
Classifier: Topic :: Internet :: WWW/HTTP
Classifier: Topic :: Internet :: WWW/HTTP :: Dynamic Content
